eem_py/__init__.py
eem_py/signature.py
eem_py/url.py
eem_py-0.0.0.dist-info/DESCRIPTION.rst
eem_py-0.0.0.dist-info/METADATA
eem_py-0.0.0.dist-info/RECORD
eem_py-0.0.0.dist-info/WHEEL
eem_py-0.0.0.dist-info/metadata.json
eem_py-0.0.0.dist-info/top_level.txt
