Metadata-Version: 2.0
Name: eem-py
Version: 0.0.0
Summary: Python module to sign and validate "eem" image manipulation URIs.
Home-page: https://github.com/eemagery
Author: eemagery
Author-email: UNKNOWN
License: MIT
Keywords: image photo manipulate crop resize eem
Platform: UNKNOWN
Classifier: Development Status :: 3 - Alpha
Classifier: Intended Audience :: Developers
Classifier: License :: OSI Approved :: MIT License
Classifier: Programming Language :: Python :: 2
Classifier: Programming Language :: Python :: 2.7
Classifier: Programming Language :: Python :: 3
Classifier: Programming Language :: Python :: 3.3
Classifier: Programming Language :: Python :: 3.4
Classifier: Programming Language :: Python :: 3.5
Requires-Dist: six
